README.rst
setup.cfg
setup.py
hdfscontents/__init__.py
hdfscontents/hdfscheckpoints.py
hdfscontents/hdfsio.py
hdfscontents/hdfsmanager.py
jupyter_hdfscontents.egg-info/PKG-INFO
jupyter_hdfscontents.egg-info/SOURCES.txt
jupyter_hdfscontents.egg-info/dependency_links.txt
jupyter_hdfscontents.egg-info/requires.txt
jupyter_hdfscontents.egg-info/top_level.txt
tests/__init__.py
tests/runall.py