Metadata-Version: 1.1
Name: jupyter-hdfscontents
Version: 0.2
Summary: Jupyter content manager that uses the HDFS filesystem
Home-page: https://github.com/alshishtawy/hdfscontents
Author: Ahmad Al-Shishtawy
Author-email: alshishtawy@gmail.com
License: Apache License 2.0
Download-URL: https://github.com/alshishtawy/hdfscontents/archive/0.2.tar.gz
Keywords: Jupyter,HDFS
Platform: UNKNOWN
Classifier: Development Status :: 3 - Alpha
Classifier: Framework :: IPython
Classifier: Topic :: Utilities
Classifier: License :: OSI Approved :: Apache Software License
Classifier: Programming Language :: Python :: 2.7
Classifier: Programming Language :: Python :: 3
